python_qiwi/__init__.py
python_qiwi/python_qiwi.py
python_qiwi-1.3.0.dist-info/LICENSE
python_qiwi-1.3.0.dist-info/METADATA
python_qiwi-1.3.0.dist-info/WHEEL
python_qiwi-1.3.0.dist-info/top_level.txt
python_qiwi-1.3.0.dist-info/RECORD
