Metadata-Version: 2.1
Name: python-qiwi
Version: 1.3.0
Summary: library for easy work with qiwi wallet
Home-page: https://github.com/lev007-ops/python-qiwi
Author: Lev
Author-email: lev_bariakh@icloud.com
License: UNKNOWN
Platform: UNKNOWN
Classifier: Programming Language :: Python :: 3
Classifier: License :: OSI Approved :: MIT License
Classifier: Operating System :: OS Independent
License-File: LICENSE
